setup.py
distill/__init__.py
distill/application.py
distill/decorators.py
distill/exceptions.py
distill/helpers.py
distill/renderers.py
distill/request.py
distill/response.py
distill/sessions.py
distill_framework.egg-info/PKG-INFO
distill_framework.egg-info/SOURCES.txt
distill_framework.egg-info/dependency_links.txt
distill_framework.egg-info/requires.txt
distill_framework.egg-info/top_level.txt